LICENSE.md
MANIFEST.in
README.md
README.rst
pyproject.toml
setup.cfg
setup.py
pyamr/__init__.py
pyamr/__main__.py
pyamr.egg-info/PKG-INFO
pyamr.egg-info/SOURCES.txt
pyamr.egg-info/dependency_links.txt
pyamr.egg-info/requires.txt
pyamr.egg-info/top_level.txt
pyamr/core/__init__.py
pyamr/core/acsi.py
pyamr/core/asai.py
pyamr/core/dri.py
pyamr/core/freq.py
pyamr/core/mari.py
pyamr/core/sari.py
pyamr/core/sart.py
pyamr/core/regression/__init__.py
pyamr/core/regression/arima.py
pyamr/core/regression/pyarima.py
pyamr/core/regression/pyarima2.py
pyamr/core/regression/sarimax.py
pyamr/core/regression/theilsens.py
pyamr/core/regression/wbase.py
pyamr/core/regression/wls.py
pyamr/core/regression/wlsarma.py
pyamr/core/regression/wreg.py
pyamr/core/regression/wregression.py
pyamr/core/stats/__init__.py
pyamr/core/stats/adfuller.py
pyamr/core/stats/correlation.py
pyamr/core/stats/kendall.py
pyamr/core/stats/kpss.py
pyamr/core/stats/stationarity.py
pyamr/core/stats/wbase.py
pyamr/core/table/__init__.py
pyamr/core/table/acronym.py
pyamr/core/table/antibiotic.py
pyamr/core/table/organism.py
pyamr/core/table/utils.py
pyamr/datasets/__init__.py
pyamr/datasets/clean.py
pyamr/datasets/load.py
pyamr/datasets/registries.py
pyamr/datasets/microbiology/__init__.py
pyamr/datasets/microbiology/create_quickimport.py
pyamr/datasets/microbiology/create_susceptibility.py
pyamr/datasets/microbiology/quickimport_create.py
pyamr/datasets/microbiology/quickimport_run.py
pyamr/datasets/microbiology/test.py
pyamr/graphics/__init__.py
pyamr/graphics/antibiogram.py
pyamr/graphics/table_graph.py
pyamr/graphics/utils_to_delete.py
pyamr/metrics/__init__.py
pyamr/metrics/scores.py
pyamr/metrics/weights.py
pyamr/tests/__init__.py
pyamr/tests/test_manual.py
pyamr/tests/test_scripts.py
pyamr/utils/__init__.py
pyamr/utils/plot.py
pyamr/utils/io/__init__.py
pyamr/utils/io/read.py