Metadata-Version: 2.1
Name: pyamr
Version: 0.0.6
Summary: A lightweight package to compute Antimicrobial Resistance (AMR) metrics.
Home-page: https://bahp.github.io/pyAMR/
Author: Bernard Hernandez
Author-email: Bernard Hernandez <b.hernandez-perez@imperial.ac.uk>
License: MIT
Project-URL: Source, https://github.com/bahp/pyamr/
Project-URL: Documentation, https://bahp.github.io/pyAMR/
Project-URL: Bug Tracker, https://github.com/bahp/pyAMR/issues
Keywords: AMR
Classifier: Intended Audience :: Developers
Classifier: License :: OSI Approved :: BSD License
Classifier: Operating System :: OS Independent
Classifier: Programming Language :: Python
Classifier: Programming Language :: Python :: 3
Classifier: Programming Language :: Python :: 3 :: Only
Classifier: Programming Language :: Python :: 3.6
Classifier: Programming Language :: Python :: 3.7
Classifier: Programming Language :: Python :: 3.8
Provides-Extra: test
Provides-Extra: doc
Provides-Extra: plot
License-File: LICENSE.md
